package in.gov.hp.Aadhaar_HP.SRDH;

import android.os.AsyncTask;
import android.widget.ProgressBar;
import android.widget.Toast;
import java.util.List;

class b
  extends AsyncTask
{
  String a = null;
  
  b(AdvancedListFive paramAdvancedListFive) {}
  
  /* Error */
  protected String a(String... paramVarArgs)
  {
    // Byte code:
    //   0: aload_0
    //   1: getfield 12	in/gov/hp/Aadhaar_HP/SRDH/b:b	Lin/gov/hp/Aadhaar_HP/SRDH/AdvancedListFive;
    //   4: new 27	java/net/URL
    //   7: dup
    //   8: ldc 29
    //   10: invokespecial 32	java/net/URL:<init>	(Ljava/lang/String;)V
    //   13: putfield 38	in/gov/hp/Aadhaar_HP/SRDH/AdvancedListFive:i	Ljava/net/URL;
    //   16: aload_0
    //   17: getfield 12	in/gov/hp/Aadhaar_HP/SRDH/b:b	Lin/gov/hp/Aadhaar_HP/SRDH/AdvancedListFive;
    //   20: aload_0
    //   21: getfield 12	in/gov/hp/Aadhaar_HP/SRDH/b:b	Lin/gov/hp/Aadhaar_HP/SRDH/AdvancedListFive;
    //   24: getfield 38	in/gov/hp/Aadhaar_HP/SRDH/AdvancedListFive:i	Ljava/net/URL;
    //   27: invokevirtual 42	java/net/URL:openConnection	()Ljava/net/URLConnection;
    //   30: checkcast 44	java/net/HttpURLConnection
    //   33: putfield 48	in/gov/hp/Aadhaar_HP/SRDH/AdvancedListFive:j	Ljava/net/HttpURLConnection;
    //   36: aload_0
    //   37: getfield 12	in/gov/hp/Aadhaar_HP/SRDH/b:b	Lin/gov/hp/Aadhaar_HP/SRDH/AdvancedListFive;
    //   40: getfield 48	in/gov/hp/Aadhaar_HP/SRDH/AdvancedListFive:j	Ljava/net/HttpURLConnection;
    //   43: iconst_1
    //   44: invokevirtual 52	java/net/HttpURLConnection:setDoOutput	(Z)V
    //   47: aload_0
    //   48: getfield 12	in/gov/hp/Aadhaar_HP/SRDH/b:b	Lin/gov/hp/Aadhaar_HP/SRDH/AdvancedListFive;
    //   51: getfield 48	in/gov/hp/Aadhaar_HP/SRDH/AdvancedListFive:j	Ljava/net/HttpURLConnection;
    //   54: ldc 54
    //   56: invokevirtual 57	java/net/HttpURLConnection:setRequestMethod	(Ljava/lang/String;)V
    //   59: aload_0
    //   60: getfield 12	in/gov/hp/Aadhaar_HP/SRDH/b:b	Lin/gov/hp/Aadhaar_HP/SRDH/AdvancedListFive;
    //   63: getfield 48	in/gov/hp/Aadhaar_HP/SRDH/AdvancedListFive:j	Ljava/net/HttpURLConnection;
    //   66: iconst_0
    //   67: invokevirtual 60	java/net/HttpURLConnection:setUseCaches	(Z)V
    //   70: aload_0
    //   71: getfield 12	in/gov/hp/Aadhaar_HP/SRDH/b:b	Lin/gov/hp/Aadhaar_HP/SRDH/AdvancedListFive;
    //   74: getfield 48	in/gov/hp/Aadhaar_HP/SRDH/AdvancedListFive:j	Ljava/net/HttpURLConnection;
    //   77: sipush 20000
    //   80: invokevirtual 64	java/net/HttpURLConnection:setConnectTimeout	(I)V
    //   83: aload_0
    //   84: getfield 12	in/gov/hp/Aadhaar_HP/SRDH/b:b	Lin/gov/hp/Aadhaar_HP/SRDH/AdvancedListFive;
    //   87: getfield 48	in/gov/hp/Aadhaar_HP/SRDH/AdvancedListFive:j	Ljava/net/HttpURLConnection;
    //   90: sipush 20000
    //   93: invokevirtual 67	java/net/HttpURLConnection:setReadTimeout	(I)V
    //   96: aload_0
    //   97: getfield 12	in/gov/hp/Aadhaar_HP/SRDH/b:b	Lin/gov/hp/Aadhaar_HP/SRDH/AdvancedListFive;
    //   100: getfield 48	in/gov/hp/Aadhaar_HP/SRDH/AdvancedListFive:j	Ljava/net/HttpURLConnection;
    //   103: ldc 69
    //   105: ldc 71
    //   107: invokevirtual 75	java/net/HttpURLConnection:setRequestProperty	(Ljava/lang/String;Ljava/lang/String;)V
    //   110: aload_0
    //   111: getfield 12	in/gov/hp/Aadhaar_HP/SRDH/b:b	Lin/gov/hp/Aadhaar_HP/SRDH/AdvancedListFive;
    //   114: getfield 48	in/gov/hp/Aadhaar_HP/SRDH/AdvancedListFive:j	Ljava/net/HttpURLConnection;
    //   117: invokevirtual 78	java/net/HttpURLConnection:connect	()V
    //   120: new 80	org/json/JSONStringer
    //   123: dup
    //   124: invokespecial 81	org/json/JSONStringer:<init>	()V
    //   127: invokevirtual 85	org/json/JSONStringer:object	()Lorg/json/JSONStringer;
    //   130: ldc 87
    //   132: invokevirtual 91	org/json/JSONStringer:key	(Ljava/lang/String;)Lorg/json/JSONStringer;
    //   135: invokevirtual 85	org/json/JSONStringer:object	()Lorg/json/JSONStringer;
    //   138: ldc 93
    //   140: invokevirtual 91	org/json/JSONStringer:key	(Ljava/lang/String;)Lorg/json/JSONStringer;
    //   143: aload_1
    //   144: iconst_0
    //   145: aaload
    //   146: invokevirtual 97	org/json/JSONStringer:value	(Ljava/lang/Object;)Lorg/json/JSONStringer;
    //   149: ldc 99
    //   151: invokevirtual 91	org/json/JSONStringer:key	(Ljava/lang/String;)Lorg/json/JSONStringer;
    //   154: aload_1
    //   155: iconst_1
    //   156: aaload
    //   157: invokevirtual 97	org/json/JSONStringer:value	(Ljava/lang/Object;)Lorg/json/JSONStringer;
    //   160: ldc 101
    //   162: invokevirtual 91	org/json/JSONStringer:key	(Ljava/lang/String;)Lorg/json/JSONStringer;
    //   165: aload_1
    //   166: iconst_2
    //   167: aaload
    //   168: invokevirtual 97	org/json/JSONStringer:value	(Ljava/lang/Object;)Lorg/json/JSONStringer;
    //   171: ldc 103
    //   173: invokevirtual 91	org/json/JSONStringer:key	(Ljava/lang/String;)Lorg/json/JSONStringer;
    //   176: aload_1
    //   177: iconst_3
    //   178: aaload
    //   179: invokevirtual 97	org/json/JSONStringer:value	(Ljava/lang/Object;)Lorg/json/JSONStringer;
    //   182: ldc 105
    //   184: invokevirtual 91	org/json/JSONStringer:key	(Ljava/lang/String;)Lorg/json/JSONStringer;
    //   187: aload_1
    //   188: iconst_4
    //   189: aaload
    //   190: invokevirtual 97	org/json/JSONStringer:value	(Ljava/lang/Object;)Lorg/json/JSONStringer;
    //   193: invokevirtual 108	org/json/JSONStringer:endObject	()Lorg/json/JSONStringer;
    //   196: invokevirtual 108	org/json/JSONStringer:endObject	()Lorg/json/JSONStringer;
    //   199: astore_1
    //   200: getstatic 114	java/lang/System:out	Ljava/io/PrintStream;
    //   203: new 116	java/lang/StringBuilder
    //   206: dup
    //   207: invokespecial 117	java/lang/StringBuilder:<init>	()V
    //   210: ldc 119
    //   212: invokevirtual 123	java/lang/StringBuilder:append	(Ljava/lang/String;)Ljava/lang/StringBuilder;
    //   215: aload_1
    //   216: invokevirtual 127	org/json/JSONStringer:toString	()Ljava/lang/String;
    //   219: invokevirtual 123	java/lang/StringBuilder:append	(Ljava/lang/String;)Ljava/lang/StringBuilder;
    //   222: invokevirtual 128	java/lang/StringBuilder:toString	()Ljava/lang/String;
    //   225: invokevirtual 133	java/io/PrintStream:println	(Ljava/lang/String;)V
    //   228: new 135	java/io/OutputStreamWriter
    //   231: dup
    //   232: aload_0
    //   233: getfield 12	in/gov/hp/Aadhaar_HP/SRDH/b:b	Lin/gov/hp/Aadhaar_HP/SRDH/AdvancedListFive;
    //   236: getfield 48	in/gov/hp/Aadhaar_HP/SRDH/AdvancedListFive:j	Ljava/net/HttpURLConnection;
    //   239: invokevirtual 139	java/net/HttpURLConnection:getOutputStream	()Ljava/io/OutputStream;
    //   242: invokespecial 142	java/io/OutputStreamWriter:<init>	(Ljava/io/OutputStream;)V
    //   245: astore_3
    //   246: aload_3
    //   247: aload_1
    //   248: invokevirtual 127	org/json/JSONStringer:toString	()Ljava/lang/String;
    //   251: invokevirtual 145	java/io/OutputStreamWriter:write	(Ljava/lang/String;)V
    //   254: aload_3
    //   255: invokevirtual 148	java/io/OutputStreamWriter:close	()V
    //   258: aload_0
    //   259: getfield 12	in/gov/hp/Aadhaar_HP/SRDH/b:b	Lin/gov/hp/Aadhaar_HP/SRDH/AdvancedListFive;
    //   262: getfield 48	in/gov/hp/Aadhaar_HP/SRDH/AdvancedListFive:j	Ljava/net/HttpURLConnection;
    //   265: invokevirtual 152	java/net/HttpURLConnection:getResponseCode	()I
    //   268: istore_2
    //   269: iload_2
    //   270: sipush 200
    //   273: if_icmpne +194 -> 467
    //   276: getstatic 114	java/lang/System:out	Ljava/io/PrintStream;
    //   279: new 116	java/lang/StringBuilder
    //   282: dup
    //   283: invokespecial 117	java/lang/StringBuilder:<init>	()V
    //   286: iload_2
    //   287: invokevirtual 155	java/lang/StringBuilder:append	(I)Ljava/lang/StringBuilder;
    //   290: ldc -99
    //   292: invokevirtual 123	java/lang/StringBuilder:append	(Ljava/lang/String;)Ljava/lang/StringBuilder;
    //   295: invokevirtual 128	java/lang/StringBuilder:toString	()Ljava/lang/String;
    //   298: invokevirtual 133	java/io/PrintStream:println	(Ljava/lang/String;)V
    //   301: new 159	java/io/BufferedReader
    //   304: dup
    //   305: new 161	java/io/InputStreamReader
    //   308: dup
    //   309: aload_0
    //   310: getfield 12	in/gov/hp/Aadhaar_HP/SRDH/b:b	Lin/gov/hp/Aadhaar_HP/SRDH/AdvancedListFive;
    //   313: getfield 48	in/gov/hp/Aadhaar_HP/SRDH/AdvancedListFive:j	Ljava/net/HttpURLConnection;
    //   316: invokevirtual 165	java/net/HttpURLConnection:getInputStream	()Ljava/io/InputStream;
    //   319: ldc -89
    //   321: invokespecial 170	java/io/InputStreamReader:<init>	(Ljava/io/InputStream;Ljava/lang/String;)V
    //   324: invokespecial 173	java/io/BufferedReader:<init>	(Ljava/io/Reader;)V
    //   327: astore_1
    //   328: aload_1
    //   329: invokevirtual 176	java/io/BufferedReader:readLine	()Ljava/lang/String;
    //   332: astore_3
    //   333: aload_3
    //   334: ifnull +106 -> 440
    //   337: aload_0
    //   338: getfield 12	in/gov/hp/Aadhaar_HP/SRDH/b:b	Lin/gov/hp/Aadhaar_HP/SRDH/AdvancedListFive;
    //   341: getfield 180	in/gov/hp/Aadhaar_HP/SRDH/AdvancedListFive:k	Ljava/lang/StringBuilder;
    //   344: new 116	java/lang/StringBuilder
    //   347: dup
    //   348: invokespecial 117	java/lang/StringBuilder:<init>	()V
    //   351: aload_3
    //   352: invokevirtual 123	java/lang/StringBuilder:append	(Ljava/lang/String;)Ljava/lang/StringBuilder;
    //   355: ldc -74
    //   357: invokevirtual 123	java/lang/StringBuilder:append	(Ljava/lang/String;)Ljava/lang/StringBuilder;
    //   360: invokevirtual 128	java/lang/StringBuilder:toString	()Ljava/lang/String;
    //   363: invokevirtual 123	java/lang/StringBuilder:append	(Ljava/lang/String;)Ljava/lang/StringBuilder;
    //   366: pop
    //   367: getstatic 114	java/lang/System:out	Ljava/io/PrintStream;
    //   370: new 116	java/lang/StringBuilder
    //   373: dup
    //   374: invokespecial 117	java/lang/StringBuilder:<init>	()V
    //   377: aload_0
    //   378: getfield 12	in/gov/hp/Aadhaar_HP/SRDH/b:b	Lin/gov/hp/Aadhaar_HP/SRDH/AdvancedListFive;
    //   381: getfield 180	in/gov/hp/Aadhaar_HP/SRDH/AdvancedListFive:k	Ljava/lang/StringBuilder;
    //   384: invokevirtual 128	java/lang/StringBuilder:toString	()Ljava/lang/String;
    //   387: invokevirtual 123	java/lang/StringBuilder:append	(Ljava/lang/String;)Ljava/lang/StringBuilder;
    //   390: ldc -99
    //   392: invokevirtual 123	java/lang/StringBuilder:append	(Ljava/lang/String;)Ljava/lang/StringBuilder;
    //   395: invokevirtual 128	java/lang/StringBuilder:toString	()Ljava/lang/String;
    //   398: invokevirtual 133	java/io/PrintStream:println	(Ljava/lang/String;)V
    //   401: goto -73 -> 328
    //   404: astore_1
    //   405: aload_1
    //   406: invokevirtual 185	java/net/MalformedURLException:printStackTrace	()V
    //   409: aload_0
    //   410: getfield 12	in/gov/hp/Aadhaar_HP/SRDH/b:b	Lin/gov/hp/Aadhaar_HP/SRDH/AdvancedListFive;
    //   413: getfield 48	in/gov/hp/Aadhaar_HP/SRDH/AdvancedListFive:j	Ljava/net/HttpURLConnection;
    //   416: ifnull +13 -> 429
    //   419: aload_0
    //   420: getfield 12	in/gov/hp/Aadhaar_HP/SRDH/b:b	Lin/gov/hp/Aadhaar_HP/SRDH/AdvancedListFive;
    //   423: getfield 48	in/gov/hp/Aadhaar_HP/SRDH/AdvancedListFive:j	Ljava/net/HttpURLConnection;
    //   426: invokevirtual 188	java/net/HttpURLConnection:disconnect	()V
    //   429: aload_0
    //   430: getfield 12	in/gov/hp/Aadhaar_HP/SRDH/b:b	Lin/gov/hp/Aadhaar_HP/SRDH/AdvancedListFive;
    //   433: getfield 180	in/gov/hp/Aadhaar_HP/SRDH/AdvancedListFive:k	Ljava/lang/StringBuilder;
    //   436: invokevirtual 128	java/lang/StringBuilder:toString	()Ljava/lang/String;
    //   439: areturn
    //   440: aload_1
    //   441: invokevirtual 189	java/io/BufferedReader:close	()V
    //   444: aload_0
    //   445: getfield 12	in/gov/hp/Aadhaar_HP/SRDH/b:b	Lin/gov/hp/Aadhaar_HP/SRDH/AdvancedListFive;
    //   448: getfield 48	in/gov/hp/Aadhaar_HP/SRDH/AdvancedListFive:j	Ljava/net/HttpURLConnection;
    //   451: ifnull -22 -> 429
    //   454: aload_0
    //   455: getfield 12	in/gov/hp/Aadhaar_HP/SRDH/b:b	Lin/gov/hp/Aadhaar_HP/SRDH/AdvancedListFive;
    //   458: getfield 48	in/gov/hp/Aadhaar_HP/SRDH/AdvancedListFive:j	Ljava/net/HttpURLConnection;
    //   461: invokevirtual 188	java/net/HttpURLConnection:disconnect	()V
    //   464: goto -35 -> 429
    //   467: getstatic 114	java/lang/System:out	Ljava/io/PrintStream;
    //   470: aload_0
    //   471: getfield 12	in/gov/hp/Aadhaar_HP/SRDH/b:b	Lin/gov/hp/Aadhaar_HP/SRDH/AdvancedListFive;
    //   474: getfield 48	in/gov/hp/Aadhaar_HP/SRDH/AdvancedListFive:j	Ljava/net/HttpURLConnection;
    //   477: invokevirtual 192	java/net/HttpURLConnection:getResponseMessage	()Ljava/lang/String;
    //   480: invokevirtual 133	java/io/PrintStream:println	(Ljava/lang/String;)V
    //   483: goto -39 -> 444
    //   486: astore_1
    //   487: aload_1
    //   488: invokevirtual 193	java/io/IOException:printStackTrace	()V
    //   491: aload_0
    //   492: getfield 12	in/gov/hp/Aadhaar_HP/SRDH/b:b	Lin/gov/hp/Aadhaar_HP/SRDH/AdvancedListFive;
    //   495: getfield 48	in/gov/hp/Aadhaar_HP/SRDH/AdvancedListFive:j	Ljava/net/HttpURLConnection;
    //   498: ifnull -69 -> 429
    //   501: aload_0
    //   502: getfield 12	in/gov/hp/Aadhaar_HP/SRDH/b:b	Lin/gov/hp/Aadhaar_HP/SRDH/AdvancedListFive;
    //   505: getfield 48	in/gov/hp/Aadhaar_HP/SRDH/AdvancedListFive:j	Ljava/net/HttpURLConnection;
    //   508: invokevirtual 188	java/net/HttpURLConnection:disconnect	()V
    //   511: goto -82 -> 429
    //   514: astore_1
    //   515: aload_1
    //   516: invokevirtual 194	org/json/JSONException:printStackTrace	()V
    //   519: aload_0
    //   520: getfield 12	in/gov/hp/Aadhaar_HP/SRDH/b:b	Lin/gov/hp/Aadhaar_HP/SRDH/AdvancedListFive;
    //   523: getfield 48	in/gov/hp/Aadhaar_HP/SRDH/AdvancedListFive:j	Ljava/net/HttpURLConnection;
    //   526: ifnull -97 -> 429
    //   529: aload_0
    //   530: getfield 12	in/gov/hp/Aadhaar_HP/SRDH/b:b	Lin/gov/hp/Aadhaar_HP/SRDH/AdvancedListFive;
    //   533: getfield 48	in/gov/hp/Aadhaar_HP/SRDH/AdvancedListFive:j	Ljava/net/HttpURLConnection;
    //   536: invokevirtual 188	java/net/HttpURLConnection:disconnect	()V
    //   539: goto -110 -> 429
    //   542: astore_1
    //   543: aload_0
    //   544: getfield 12	in/gov/hp/Aadhaar_HP/SRDH/b:b	Lin/gov/hp/Aadhaar_HP/SRDH/AdvancedListFive;
    //   547: getfield 48	in/gov/hp/Aadhaar_HP/SRDH/AdvancedListFive:j	Ljava/net/HttpURLConnection;
    //   550: ifnull +13 -> 563
    //   553: aload_0
    //   554: getfield 12	in/gov/hp/Aadhaar_HP/SRDH/b:b	Lin/gov/hp/Aadhaar_HP/SRDH/AdvancedListFive;
    //   557: getfield 48	in/gov/hp/Aadhaar_HP/SRDH/AdvancedListFive:j	Ljava/net/HttpURLConnection;
    //   560: invokevirtual 188	java/net/HttpURLConnection:disconnect	()V
    //   563: aload_1
    //   564: athrow
    // Local variable table:
    //   start	length	slot	name	signature
    //   0	565	0	this	b
    //   0	565	1	paramVarArgs	String[]
    //   268	19	2	i	int
    //   245	107	3	localObject	Object
    // Exception table:
    //   from	to	target	type
    //   0	269	404	java/net/MalformedURLException
    //   276	328	404	java/net/MalformedURLException
    //   328	333	404	java/net/MalformedURLException
    //   337	401	404	java/net/MalformedURLException
    //   440	444	404	java/net/MalformedURLException
    //   467	483	404	java/net/MalformedURLException
    //   0	269	486	java/io/IOException
    //   276	328	486	java/io/IOException
    //   328	333	486	java/io/IOException
    //   337	401	486	java/io/IOException
    //   440	444	486	java/io/IOException
    //   467	483	486	java/io/IOException
    //   0	269	514	org/json/JSONException
    //   276	328	514	org/json/JSONException
    //   328	333	514	org/json/JSONException
    //   337	401	514	org/json/JSONException
    //   440	444	514	org/json/JSONException
    //   467	483	514	org/json/JSONException
    //   0	269	542	finally
    //   276	328	542	finally
    //   328	333	542	finally
    //   337	401	542	finally
    //   405	409	542	finally
    //   440	444	542	finally
    //   467	483	542	finally
    //   487	491	542	finally
    //   515	519	542	finally
  }
  
  protected void a(String paramString)
  {
    super.onPostExecute(paramString);
    b.h = z.a(paramString);
    if (b.h.isEmpty()) {
      Toast.makeText(b.getApplicationContext(), "No match found", 1).show();
    }
    if (b.h.size() >= 100)
    {
      b.b();
      Toast.makeText(b.getApplicationContext(), "Only the top 100 results are being displayed. Please be more specific. ", 1).show();
    }
    for (;;)
    {
      b.g.remove(this);
      if (b.g.size() == 0) {
        b.f.setVisibility(4);
      }
      return;
      b.b();
    }
  }
  
  protected void onPreExecute()
  {
    super.onPreExecute();
    if (b.g.size() == 0) {
      b.f.setVisibility(0);
    }
    b.g.add(this);
  }
}

/* Location:
 * Qualified Name:     in.gov.hp.Aadhaar_HP.SRDH.b
 * Java Class Version: 6 (50.0)
 * JD-Core Version:    0.7.1
 */